AUTHORS
HISTORY.rst
LICENSE
MANIFEST.in
README.rst
setup.cfg
setup.py
django_pipeline_no_future.egg-info/PKG-INFO
django_pipeline_no_future.egg-info/SOURCES.txt
django_pipeline_no_future.egg-info/dependency_links.txt
django_pipeline_no_future.egg-info/not-zip-safe
django_pipeline_no_future.egg-info/top_level.txt
docs/Makefile
docs/compilers.rst
docs/compressors.rst
docs/conf.py
docs/configuration.rst
docs/index.rst
docs/installation.rst
docs/make.bat
docs/signals.rst
docs/storages.rst
docs/templates.rst
docs/usage.rst
docs/using.rst
pipeline/__init__.py
pipeline/collector.py
pipeline/conf.py
pipeline/exceptions.py
pipeline/finders.py
pipeline/glob.py
pipeline/manifest.py
pipeline/middleware.py
pipeline/packager.py
pipeline/signals.py
pipeline/storage.py
pipeline/utils.py
pipeline/views.py
pipeline/compilers/__init__.py
pipeline/compilers/coffee.py
pipeline/compilers/es6.py
pipeline/compilers/less.py
pipeline/compilers/livescript.py
pipeline/compilers/sass.py
pipeline/compilers/stylus.py
pipeline/compressors/__init__.py
pipeline/compressors/closure.py
pipeline/compressors/cssmin.py
pipeline/compressors/csstidy.py
pipeline/compressors/jsmin.py
pipeline/compressors/slimit.py
pipeline/compressors/uglifyjs.py
pipeline/compressors/yuglify.py
pipeline/compressors/yui.py
pipeline/jinja2/__init__.py
pipeline/jinja2/pipeline/css.jinja
pipeline/jinja2/pipeline/inline_js.jinja
pipeline/jinja2/pipeline/js.jinja
pipeline/templates/pipeline/compile_error.html
pipeline/templates/pipeline/css.html
pipeline/templates/pipeline/css.jinja
pipeline/templates/pipeline/inline_js.html
pipeline/templates/pipeline/inline_js.jinja
pipeline/templates/pipeline/js.html
pipeline/templates/pipeline/js.jinja
pipeline/templatetags/__init__.py
pipeline/templatetags/pipeline.py
tests/__init__.py
tests/models.py
tests/package.json
tests/settings.py
tests/urls.py
tests/utils.py
tests/views.py
tests/assets/compilers/coffee/expected.js
tests/assets/compilers/coffee/input.coffee
tests/assets/compilers/es6/expected.js
tests/assets/compilers/es6/input.es6
tests/assets/compilers/less/expected.css
tests/assets/compilers/less/input.less
tests/assets/compilers/livescript/expected.js
tests/assets/compilers/livescript/input.ls
