Metadata-Version: 1.1
Name: django-pipeline-no-future
Version: 1.6.8.1
Summary: Pipeline is an asset packaging library for Django.
Home-page: https://github.com/robinchew/django-pipeline
Author: Robin Chew
Author-email: robin@obsi.com.au
License: MIT
Platform: UNKNOWN
Classifier: Environment :: Web Environment
Classifier: Intended Audience :: Developers
Classifier: Development Status :: 5 - Production/Stable
Classifier: License :: OSI Approved :: MIT License
Classifier: Operating System :: OS Independent
Classifier: Programming Language :: Python
Classifier: Programming Language :: Python :: 3
Classifier: Topic :: Utilities
